CHANGES.txt
CONTRIBUTORS.txt
MANIFEST.in
README.txt
setup.cfg
setup.py
docs/HISTORY.txt
docs/INSTALL.txt
docs/LICENSE.GPL
docs/LICENSE.txt
xhostplus/__init__.py
xhostplus.social.egg-info/PKG-INFO
xhostplus.social.egg-info/SOURCES.txt
xhostplus.social.egg-info/dependency_links.txt
xhostplus.social.egg-info/entry_points.txt
xhostplus.social.egg-info/namespace_packages.txt
xhostplus.social.egg-info/not-zip-safe
xhostplus.social.egg-info/paster_plugins.txt
xhostplus.social.egg-info/requires.txt
xhostplus.social.egg-info/top_level.txt
xhostplus/social/README.txt
xhostplus/social/__init__.py
xhostplus/social/config.py
xhostplus/social/configure.zcml
xhostplus/social/permissions.zcml
xhostplus/social/upgrades.py
xhostplus/social/browser/__init__.py
xhostplus/social/browser/buttons.pt
xhostplus/social/browser/configlets.py
xhostplus/social/browser/configure.zcml
xhostplus/social/browser/opengraph.pt
xhostplus/social/browser/social_configuration.pt
xhostplus/social/browser/viewlets.py
xhostplus/social/browser/images/2-klick-logo.jpg
xhostplus/social/browser/images/configuration_icon.png
xhostplus/social/browser/images/dummy_facebook_de.png
xhostplus/social/browser/images/dummy_facebook_en.png
xhostplus/social/browser/images/dummy_googleplus_en.png
xhostplus/social/browser/images/dummy_linkedin_en.png
xhostplus/social/browser/images/dummy_twitter_de.png
xhostplus/social/browser/images/dummy_twitter_en.png
xhostplus/social/browser/images/socialshareprivacy_info.png
xhostplus/social/browser/images/socialshareprivacy_on_off.png
xhostplus/social/browser/images/socialshareprivacy_settings.png
xhostplus/social/browser/javascripts/jquery.socialshareprivacy.js
xhostplus/social/browser/javascripts/xhostplus.social.js
xhostplus/social/browser/stylesheets/socialshareprivacy.css
xhostplus/social/browser/stylesheets/xhostplus.social.css
xhostplus/social/content/__init__.py
xhostplus/social/content/configure.zcml
xhostplus/social/content/extender.py
xhostplus/social/content/utilities.py
xhostplus/social/interfaces/__init__.py
xhostplus/social/interfaces/configuration.py
xhostplus/social/locales/xhostplus.social.pot
xhostplus/social/locales/de/LC_MESSAGES/xhostplus.social.mo
xhostplus/social/locales/de/LC_MESSAGES/xhostplus.social.po
xhostplus/social/locales/en/LC_MESSAGES/xhostplus.social.mo
xhostplus/social/locales/en/LC_MESSAGES/xhostplus.social.po
