Metadata-Version: 1.1
Name: xhostplus.social
Version: 1.4.6
Summary: Displays social buttons (facebook, google+, twitter, linkedin) on the Plone site.
Home-page: http://www.xhostplus.at/de/services/plone-downlods
Author: UNKNOWN
Author-email: UNKNOWN
License: GPL
Platform: UNKNOWN
Classifier: Framework :: Plone
Classifier: Intended Audience :: Developers
Classifier: License :: OSI Approved :: GNU General Public License (GPL)
